typefire/__init__.py
typefire/tool.py
typefire/typefire.py
typefire-0.0.3.dist-info/LICENSE
typefire-0.0.3.dist-info/METADATA
typefire-0.0.3.dist-info/WHEEL
typefire-0.0.3.dist-info/top_level.txt
typefire-0.0.3.dist-info/RECORD
