Metadata-Version: 2.1
Name: typefire
Version: 0.0.3
Summary: 基于类型注解的自定义类型转换, 可用于拓展 fire 解析类型
Home-page: https://github.com/luxuncang/typefire
Author: ShengXin Lu
Author-email: luxuncang@qq.com
License: MIT
Platform: all
Classifier: Intended Audience :: Developers
Classifier: Operating System :: OS Independent
Classifier: Natural Language :: Chinese (Simplified)
Classifier: Programming Language :: Python :: 3.5
Classifier: Programming Language :: Python :: 3.6
Classifier: Programming Language :: Python :: 3.7
Classifier: Programming Language :: Python :: 3.8
Classifier: Programming Language :: Python :: 3.9
Classifier: Programming Language :: Python :: 3.10
Classifier: Topic :: Software Development :: Libraries
License-File: LICENSE
Requires-Dist: SimilarNeuron
Requires-Dist: fire
